tracdap/rt/__init__.py
tracdap/rt/_version.py
tracdap/rt/exceptions.py
tracdap/rt/_impl/__init__.py
tracdap/rt/_impl/runtime.py
tracdap/rt/_impl/static_api.py
tracdap/rt/_impl/core/__init__.py
tracdap/rt/_impl/core/config_parser.py
tracdap/rt/_impl/core/data.py
tracdap/rt/_impl/core/guard_rails.py
tracdap/rt/_impl/core/logging.py
tracdap/rt/_impl/core/models.py
tracdap/rt/_impl/core/repos.py
tracdap/rt/_impl/core/schemas.py
tracdap/rt/_impl/core/shim.py
tracdap/rt/_impl/core/storage.py
tracdap/rt/_impl/core/struct.py
tracdap/rt/_impl/core/type_system.py
tracdap/rt/_impl/core/util.py
tracdap/rt/_impl/core/validation.py
tracdap/rt/_impl/exec/__init__.py
tracdap/rt/_impl/exec/actors.py
tracdap/rt/_impl/exec/context.py
tracdap/rt/_impl/exec/dev_mode.py
tracdap/rt/_impl/exec/engine.py
tracdap/rt/_impl/exec/functions.py
tracdap/rt/_impl/exec/graph.py
tracdap/rt/_impl/exec/graph_builder.py
tracdap/rt/_impl/ext/__init__.py
tracdap/rt/_impl/ext/sql.py
tracdap/rt/_impl/ext/storage.py
tracdap/rt/_impl/grpc/__init__.py
tracdap/rt/_impl/grpc/codec.py
tracdap/rt/_impl/grpc/server.py
tracdap/rt/_impl/grpc/tracdap/api/internal/runtime_pb2.py
tracdap/rt/_impl/grpc/tracdap/api/internal/runtime_pb2.pyi
tracdap/rt/_impl/grpc/tracdap/api/internal/runtime_pb2_grpc.py
tracdap/rt/_impl/grpc/tracdap/metadata/common_pb2.py
tracdap/rt/_impl/grpc/tracdap/metadata/common_pb2.pyi
tracdap/rt/_impl/grpc/tracdap/metadata/config_pb2.py
tracdap/rt/_impl/grpc/tracdap/metadata/config_pb2.pyi
tracdap/rt/_impl/grpc/tracdap/metadata/custom_pb2.py
tracdap/rt/_impl/grpc/tracdap/metadata/custom_pb2.pyi
tracdap/rt/_impl/grpc/tracdap/metadata/data_pb2.py
tracdap/rt/_impl/grpc/tracdap/metadata/data_pb2.pyi
tracdap/rt/_impl/grpc/tracdap/metadata/file_pb2.py
tracdap/rt/_impl/grpc/tracdap/metadata/file_pb2.pyi
tracdap/rt/_impl/grpc/tracdap/metadata/flow_pb2.py
tracdap/rt/_impl/grpc/tracdap/metadata/flow_pb2.pyi
tracdap/rt/_impl/grpc/tracdap/metadata/job_pb2.py
tracdap/rt/_impl/grpc/tracdap/metadata/job_pb2.pyi
tracdap_runtime-0.9.3.dist-info/licenses/LICENSE
tracdap_runtime-0.9.3.dist-info/METADATA
tracdap_runtime-0.9.3.dist-info/WHEEL
tracdap_runtime-0.9.3.dist-info/top_level.txt
tracdap_runtime-0.9.3.dist-info/RECORD
