Metadata-Version: 2.4
Name: tracdap-runtime
Version: 0.9.3
Summary: Portable, production-grade models in Python
Home-page: https://www.fintrac.co.uk/
Author: Martin Traverse
Author-email: martin@fintrac.co.uk
License: Apache-2.0
Project-URL: Documentation, https://docs.fintrac.co.uk/versions/latest/modelling
Project-URL: Source Code, https://github.com/finos/tracdap
Project-URL: Issue Tracker, https://github.com/finos/tracdap/issues
Platform: any
Classifier: Operating System :: OS Independent
Classifier: Programming Language :: Python :: 3
Classifier: Programming Language :: Python :: 3.9
Classifier: Programming Language :: Python :: 3.10
Classifier: Programming Language :: Python :: 3.11
Classifier: Programming Language :: Python :: 3.12
Classifier: Programming Language :: Python :: 3.13
Classifier: Intended Audience :: Developers
Classifier: Intended Audience :: End Users/Desktop
Classifier: Intended Audience :: Financial and Insurance Industry
Classifier: Topic :: Office/Business
Classifier: Topic :: Office/Business :: Financial
Classifier: Topic :: Software Development
Classifier: Topic :: Software Development :: Libraries :: Application Frameworks
Classifier: Topic :: Software Development :: Libraries :: Python Modules
Requires-Python: >=3.9
License-File: LICENSE
Requires-Dist: protobuf==6.31.1
Requires-Dist: pyarrow==21.0.0
Requires-Dist: pyyaml==6.0.2
Requires-Dist: dulwich==0.23.2
Requires-Dist: requests==2.32.4
Provides-Extra: grpc
Requires-Dist: grpcio==1.74.0; extra == "grpc"
Requires-Dist: grpcio-status==1.74.0; extra == "grpc"
Provides-Extra: pandas
Requires-Dist: pandas<2.3.0,>=1.2.0; extra == "pandas"
Requires-Dist: numpy<2.3.0,>=1.20; extra == "pandas"
Provides-Extra: polars
Requires-Dist: polars<2.0.0,>=1.0.0; extra == "polars"
Provides-Extra: pyspark
Requires-Dist: pyspark<3.6.0,>=3.0.0; extra == "pyspark"
Provides-Extra: sql
Requires-Dist: sqlalchemy<2.1.0,>=2.0.0; extra == "sql"
Provides-Extra: aws
Requires-Dist: botocore==1.39.15; extra == "aws"
Requires-Dist: boto3==1.39.15; extra == "aws"
Provides-Extra: gcp
Requires-Dist: google-auth==2.40.3; extra == "gcp"
Requires-Dist: google-api-core==2.25.1; extra == "gcp"
Requires-Dist: google-cloud-storage==3.2.0; extra == "gcp"
Requires-Dist: gcsfs==2024.3.1; extra == "gcp"
Provides-Extra: azure
Requires-Dist: azure-core==1.35.0; extra == "azure"
Requires-Dist: azure-identity==1.23.1; extra == "azure"
Requires-Dist: azure-storage-blob==12.26.0; extra == "azure"
Requires-Dist: adlfs==2024.12.0; extra == "azure"
Dynamic: license-file
